zpgdb.py
zpgdb-0.5.0.dist-info/LICENSE
zpgdb-0.5.0.dist-info/METADATA
zpgdb-0.5.0.dist-info/WHEEL
zpgdb-0.5.0.dist-info/top_level.txt
zpgdb-0.5.0.dist-info/RECORD
