Metadata-Version: 2.1
Name: zpgdb
Version: 0.5.0
Summary: Library for simple PostgreSQL connection and transaction management
Home-page: https://github.com/zanardo/zpgdb
Author: Antonio Zanardo
Author-email: zanardo@gmail.com
License: BSD
Keywords: postgresql database transaction connection
Platform: UNKNOWN
Classifier: Development Status :: 3 - Alpha
Classifier: Intended Audience :: Developers
Classifier: License :: OSI Approved :: BSD License
Classifier: Operating System :: POSIX :: Linux
Classifier: Programming Language :: Python :: 3 :: Only
Classifier: Topic :: Database
Requires-Dist: psycopg2
